README.md
setup.py
orcautomators/__init__.py
orcautomators/__main__.py
orcautomators/created_dir.py
orcautomators/exec_file.py
orcautomators/log_capture.py
orcautomators.egg-info/PKG-INFO
orcautomators.egg-info/SOURCES.txt
orcautomators.egg-info/dependency_links.txt
orcautomators.egg-info/requires.txt
orcautomators.egg-info/top_level.txt
orcautomators.egg-info/zip-safe