Metadata-Version: 1.0
Name: orcautomators
Version: 1.2
Summary: Orchestration Library for Tests
Home-page: UNKNOWN
Author: Kaue Bonfim
Author-email: koliveirab@indracompany.com
License: Indra Company
Platform: UNKNOWN
